smartpublisher/__init__.py
smartpublisher/api_server.py
smartpublisher/cli.py
smartpublisher/interactive.py
smartpublisher/published.py
smartpublisher/publisher.py
smartpublisher/validation.py
smartpublisher/http/__init__.py
smartpublisher/http/fastapi_app.py
smartpublisher/http/openapi.py
smartpublisher-0.3.0.dist-info/licenses/LICENSE
smartpublisher-0.3.0.dist-info/METADATA
smartpublisher-0.3.0.dist-info/WHEEL
smartpublisher-0.3.0.dist-info/entry_points.txt
smartpublisher-0.3.0.dist-info/top_level.txt
smartpublisher-0.3.0.dist-info/RECORD
