Metadata-Version: 2.4
Name: smartpublisher
Version: 0.3.0
Summary: Smart Publisher - CLI/API framework based on SmartSwitch
Author-email: Genropy Team <info@genropy.org>
License: MIT
Project-URL: Homepage, https://github.com/genropy/smartpublisher
Project-URL: Documentation, https://smartpublisher.readthedocs.io
Project-URL: Repository, https://github.com/genropy/smartpublisher
Project-URL: Bug Tracker, https://github.com/genropy/smartpublisher/issues
Keywords: cli,api,publisher,smartswitch,dispatcher
Classifier: Development Status :: 4 - Beta
Classifier: Intended Audience :: Developers
Classifier: License :: OSI Approved :: MIT License
Classifier: Programming Language :: Python :: 3
Classifier: Programming Language :: Python :: 3.10
Classifier: Programming Language :: Python :: 3.11
Classifier: Programming Language :: Python :: 3.12
Classifier: Topic :: Software Development :: Libraries :: Python Modules
Classifier: Topic :: System :: Shells
Requires-Python: >=3.10
License-File: LICENSE
Requires-Dist: smartswitch>=0.6.0
Requires-Dist: smartasync>=0.2.0
Requires-Dist: pydantic>=2.0
Provides-Extra: dev
Requires-Dist: pytest>=7.0; extra == "dev"
Requires-Dist: pytest-cov>=4.0; extra == "dev"
Requires-Dist: pytest-asyncio>=0.21.0; extra == "dev"
Requires-Dist: black>=23.0; extra == "dev"
Requires-Dist: ruff>=0.1.0; extra == "dev"
Requires-Dist: mypy>=1.0; extra == "dev"
Requires-Dist: textual>=0.41.0; extra == "dev"
Provides-Extra: docs
Requires-Dist: sphinx>=8.0.0; extra == "docs"
Requires-Dist: sphinx-rtd-theme>=3.0.0; extra == "docs"
Requires-Dist: sphinx-autodoc-typehints>=3.0.0; extra == "docs"
Requires-Dist: myst-parser>=4.0.0; extra == "docs"
Requires-Dist: sphinxcontrib-mermaid>=1.0.0; extra == "docs"
Provides-Extra: interactive
Requires-Dist: textual>=0.41.0; extra == "interactive"
Provides-Extra: http
Requires-Dist: fastapi>=0.104.0; extra == "http"
Requires-Dist: uvicorn[standard]>=0.24.0; extra == "http"
Requires-Dist: httpx>=0.25.0; extra == "http"
Provides-Extra: all
Requires-Dist: pytest>=7.0; extra == "all"
Requires-Dist: pytest-cov>=4.0; extra == "all"
Requires-Dist: pytest-asyncio>=0.21.0; extra == "all"
Requires-Dist: black>=23.0; extra == "all"
Requires-Dist: ruff>=0.1.0; extra == "all"
Requires-Dist: mypy>=1.0; extra == "all"
Requires-Dist: sphinx>=8.0.0; extra == "all"
Requires-Dist: sphinx-rtd-theme>=3.0.0; extra == "all"
Requires-Dist: sphinx-autodoc-typehints>=3.0.0; extra == "all"
Requires-Dist: myst-parser>=4.0.0; extra == "all"
Requires-Dist: sphinxcontrib-mermaid>=1.0.0; extra == "all"
Requires-Dist: textual>=0.41.0; extra == "all"
Requires-Dist: fastapi>=0.104.0; extra == "all"
Requires-Dist: uvicorn[standard]>=0.24.0; extra == "all"
Requires-Dist: httpx>=0.25.0; extra == "all"
Dynamic: license-file
